{
  "project_info": {
    "project_id": "marry-me-1264",
    "project_number": "850519104220",
    "name": "Marry Me"
  },
  "client": [
    {
      "client_info": {
        "mobilesdk_app_id": "1:850519104220:android:cc230524a707c31d",
        "client_id": "android:com.example.ukstechno.marryme",
        "client_type": 1,
        "android_client_info": {
          "package_name": "com.example.ukstechno.marryme",
          "certificate_hash": []
        }
      },
      "oauth_client": [
        {
          "client_id": "850519104220-pmoa2roa7i60emiqm0s1dp0mr92ptofg.apps.googleusercontent.com",
          "client_type": 1,
          "android_info": {
            "package_name": "com.example.ukstechno.marryme",
            "certificate_hash": "DD8CEB17FEF8563511264FE7D92FF843187A78C8"
          }
        },
        {
          "client_id": "850519104220-3k86spck48sh8m04t5vfs6k9muv919im.apps.googleusercontent.com",
          "client_type": 3
        }
      ],
      "api_key": [],
      "services": {
        "analytics_service": {
          "status": 1
        },
        "cloud_messaging_service": {
          "status": 1,
          "apns_config": []
        },
        "appinvite_service": {
          "status": 1,
          "other_platform_oauth_client": []
        },
        "google_signin_service": {
          "status": 2
        },
        "ads_service": {
          "status": 1
        }
      }
    }
  ],
  "client_info": [],
  "ARTIFACT_VERSION": "1"
}